common/__init__.py
common/decos.py
common/descripts.py
common/errors.py
common/metaclasses.py
common/utils.py
common/variables.py
log/__init__.py
log/client_log_config.py
log/server_log_config.py
server/__init__.py
server/add_user.py
server/config_window.py
server/core.py
server/database.py
server/main_window.py
server/remove_user.py
server/stat_window.py
unittests/__init__.py
unittests/test_client.py
unittests/test_server.py
unittests/test_utils.py
ApplicationClientServer_server-0.1.dist-info/METADATA
ApplicationClientServer_server-0.1.dist-info/WHEEL
ApplicationClientServer_server-0.1.dist-info/top_level.txt
ApplicationClientServer_server-0.1.dist-info/RECORD
