Metadata-Version: 2.1
Name: ApplicationClientServer-server
Version: 0.1
Summary: applicationclientserver_server
Author: Larisa Polozova
Author-email: larolimp@gmail.com
License: UNKNOWN
Platform: UNKNOWN
Requires-Dist: PyQt5
Requires-Dist: sqlalchemy
Requires-Dist: pycryptodome
Requires-Dist: pycryptodomex
